LICENSE
MANIFEST.in
README.md
setup.py
tuack/__init__.py
tuack/base.py
tuack/dmk.py
tuack/doc.py
tuack/dump.py
tuack/gen.py
tuack/install.py
tuack/load.py
tuack/num2chinese.py
tuack/packer.py
tuack/ren.py
tuack/test.py
tuack/tools.py
tuack.egg-info/PKG-INFO
tuack.egg-info/SOURCES.txt
tuack.egg-info/dependency_links.txt
tuack.egg-info/requires.txt
tuack.egg-info/top_level.txt
tuack/lex/compile.log
tuack/lex/compile.pyinc
tuack/lex/format-linux
tuack/lex/format-mac
tuack/lex/format-win.exe
tuack/lex/lex.l
tuack/lex/main.h
tuack/lex/yacc.y
tuack/sample/arbiter_e.noi_linux1.sample
tuack/sample/arbiter_e.sample
tuack/sample/chk.cpp
tuack/sample/contest.gitignore
tuack/sample/contest.json
tuack/sample/day.gitignore
tuack/sample/day.json
tuack/sample/empty.gitattributes
tuack/sample/empty.gitignore
tuack/sample/empty.json
tuack/sample/problem.gitattributes
tuack/sample/problem.gitignore
tuack/sample/problem.json
tuack/sample/uoj.json
tuack/sample-empty/statement/zh-cn.md
tuack/sample-problem/gen.py
tuack/sample-problem/data/1.ans
tuack/sample-problem/data/1.in
tuack/sample-problem/down/1.ans
tuack/sample-problem/down/1.in
tuack/sample-problem/pre/1.ans
tuack/sample-problem/pre/1.in
tuack/sample-problem/resources/sample.png
tuack/sample-problem/solution/zh-cn.md
tuack/sample-problem/statement/zh-cn.md
tuack/sample-problem/tables/data.pyinc
tuack/sample-problem/tables/json_data.json
tuack/sample-problem/tables/table.json
tuack/sample/precautions/zh-cn.md
tuack/templates/ccc.tex.jinja
tuack/templates/ccpc.png
tuack/templates/ccpc.tex.jinja
tuack/templates/font.html.jinja
tuack/templates/font.tex.jinja
tuack/templates/hand.tex.jinja
tuack/templates/image.html.jinja
tuack/templates/image.tex.jinja
tuack/templates/problem_base.md.jinja
tuack/templates/table.html.jinja
tuack/templates/table.md.jinja
tuack/templates/table.tex.jinja
tuack/templates/template_base.tex.jinja
tuack/templates/template_base.tex.jinja.tex
tuack/templates/tuack.cls
tuack/templates/tuoi.tex.jinja
tuack/templates/tupc.tex.jinja
tuack/templates/en/LC_MESSAGES/lang.mo
tuack/templates/en/LC_MESSAGES/lang.po
tuack/templates/zh-cn/LC_MESSAGES/lang.mo
