Metadata-Version: 2.1
Name: tuack
Version: 0.1.5.3.3
Summary: Tools for generating an Tsinghua/OI/ICPC-styled problem or contest for multiple judges.
Home-page: 
Author: Chenxu Min, Zhang Ruizhe, Liu Xiaoyi, Chen Junkun, Chen Shengqi, Luo Lingxiao, Cheng Yuxuan
Author-email: chen.xm.mu@gmail.com, 657228726@qq.com, circuitcoder0@gmail.com, 1261954105@qq.com, i@harrychen.xyz, 0.0@pku.edu.cn
License: https://git.thusaac.com/publish/tuack/blob/master/LICENSE
License-File: LICENSE
Requires-Dist: Jinja2>=3.0
Requires-Dist: natsort>=6.0.0
Requires-Dist: PyYAML>=5.1
Requires-Dist: rarfile>=3.0
Requires-Dist: Requests>=2.32
Requires-Dist: requests_toolbelt>=0.9.1
